<package>
  <description brief="A 4D (X,Y,Z, Theta) Planner for UGVs">
  
  </description>
  <author>Janosch Machowinski/Janosch.Machowinski@dfki.de</author>
  <license></license>
  <url>http://</url>
  <logo>http://</logo>
  <depend package="base/cmake" />
  <depend package="planning/sbpl" />
  <depend package="planning/motion_planning_libraries" />
  <depend package="tools/backward" />
  <depend package="control/dwa" />
  <depend package="slam/maps" />
  <depend package="slam/pcl" />
  <depend package="envire/envire_core" />
  <depend package="gui/vizkit3d_debug_drawings" />
  
    <tags>needs_opt</tags>

</package>
